bootstrap.py
buildout.cfg
setup.py
./gocept/__init__.py
./gocept/lockd/__init__.py
./gocept/lockd/client.py
./gocept/lockd/lockd.py
./gocept/lockd/tests.py
gocept/__init__.py
gocept.lockd.egg-info/PKG-INFO
gocept.lockd.egg-info/SOURCES.txt
gocept.lockd.egg-info/dependency_links.txt
gocept.lockd.egg-info/entry_points.txt
gocept.lockd.egg-info/namespace_packages.txt
gocept.lockd.egg-info/not-zip-safe
gocept.lockd.egg-info/requires.txt
gocept.lockd.egg-info/top_level.txt
gocept/lockd/README.txt
gocept/lockd/__init__.py
gocept/lockd/client.py
gocept/lockd/lockd.py
gocept/lockd/tests.py