Metadata-Version: 1.0
Name: gocept.lockd
Version: 0.1
Summary: A simple XML-RPC-based lock daemon to support fencing.
Home-page: UNKNOWN
Author: Christian Theune
Author-email: ct@gocept.com
License: ZPL 2.1
Platform: UNKNOWN
